transdoc/__cli/__init__.py
transdoc/__cli/mutex.py
transdoc/__cli/util.py
transdoc/__consts.py
transdoc/__init__.py
transdoc/__main__.py
transdoc/__rule.py
transdoc/__transform_file.py
transdoc/__transform_tree.py
transdoc/__transformer.py
transdoc/errors.py
transdoc/handlers/__init__.py
transdoc/handlers/api.py
transdoc/handlers/plaintext.py
transdoc/py.typed
transdoc/rules/__attributes.py
transdoc/rules/__file_contents.py
transdoc/rules/__init__.py
transdoc/rules/__markdown_docs_link.py
transdoc/source_pos.py
transdoc/util.py
transdoc-1.1.0.dist-info/LICENSE.md
transdoc-1.1.0.dist-info/METADATA
transdoc-1.1.0.dist-info/WHEEL
transdoc-1.1.0.dist-info/entry_points.txt
transdoc-1.1.0.dist-info/RECORD
